{
  "ui": {
    "border_primary": "#00466c",
    "border_secondary": "#4b6175",
    "header_background": "#00466c",
    "header_text": "#ffffff",
    "footer_background": "#f8f9fe",
    "footer_text": "#41474f",
    "text_primary": "#191c1f",
    "text_secondary": "#41474f",
    "text_accent": "#00466c",
    "selection_background": "#00466c",
    "selection_text": "#ffffff"
  },
  "charts": {
    "network_download": "#00466c",
    "network_upload": "#085e8e",
    "network_line": "#4b6175",
    "cpu_core_low": "#085e8e",
    "cpu_core_medium": "#00466c",
    "cpu_core_high": "#5b306d",
    "disk_read": "#00466c",
    "disk_write": "#085e8e"
  },
  "progress_bars": {
    "memory_low": "#085e8e",
    "memory_medium": "#00466c",
    "memory_high": "#5b306d",
    "disk_low": "#085e8e",
    "disk_medium": "#00466c",
    "disk_high": "#5b306d",
    "cpu_low": "#085e8e",
    "cpu_medium": "#00466c",
    "cpu_high": "#5b306d",
    "progress_background": "#eceef2"
  },
  "temperature": {
    "cold": "#085e8e",
    "warm": "#00466c",
    "hot": "#5b306d",
    "danger": "#ba1a1a"
  },
  "status": {
    "success": "#22C55E",
    "warning": "#F59E0B",
    "error": "#ba1a1a",
    "info": "#00466c"
  }
}
